abstractswarm/__init__.py
abstractswarm-0.0.1.dist-info/licenses/LICENSE
abstractswarm-0.0.1.dist-info/METADATA
abstractswarm-0.0.1.dist-info/WHEEL
abstractswarm-0.0.1.dist-info/top_level.txt
abstractswarm-0.0.1.dist-info/RECORD
