Metadata-Version: 2.4
Name: AbstractSwarm
Version: 0.0.1
Summary: A placeholder project for orchestrating multiple agents to perform higher-level tasks in coordination
Author-email: AbstractSwarm Team <contact@abstractswarm.dev>
License: MIT
Project-URL: Homepage, https://github.com/abstractswarm/abstractswarm
Project-URL: Bug Reports, https://github.com/abstractswarm/abstractswarm/issues
Project-URL: Source, https://github.com/abstractswarm/abstractswarm
Keywords: agents,swarm,orchestration,coordination,multi-agent,ai
Classifier: Development Status :: 1 - Planning
Classifier: Intended Audience :: Developers
Classifier: License :: OSI Approved :: MIT License
Classifier: Operating System :: OS Independent
Classifier: Programming Language :: Python :: 3
Classifier: Programming Language :: Python :: 3.8
Classifier: Programming Language :: Python :: 3.9
Classifier: Programming Language :: Python :: 3.10
Classifier: Programming Language :: Python :: 3.11
Classifier: Programming Language :: Python :: 3.12
Classifier: Topic :: Software Development :: Libraries :: Python Modules
Classifier: Topic :: Scientific/Engineering :: Artificial Intelligence
Requires-Python: >=3.8
License-File: LICENSE
Dynamic: license-file
